actappliance/__init__.py
actappliance/act_errors.py
actappliance/appliance.py
actappliance/helpers.py
actappliance/misc.py
actappliance/models.py
actappliance/permissions.py
actappliance/connections/__init__.py
actappliance/connections/aioconnection.py
actappliance/connections/aiorest.py
actappliance/connections/aiossh.py
actappliance/connections/connection.py
actappliance/connections/rest.py
actappliance/connections/ssh.py
act_appliance-0.9.0.dist-info/METADATA
act_appliance-0.9.0.dist-info/WHEEL
act_appliance-0.9.0.dist-info/top_level.txt
act_appliance-0.9.0.dist-info/RECORD
