Metadata-Version: 2.1
Name: act-appliance
Version: 0.9.0
Summary: An abstraction utility for actifio appliances and it is very useful
Home-page: https://github.com/Brian-Williams/actappliance
Author: Brian Williams
Author-email: briancmwilliams@gmail.com
License: UNKNOWN
Keywords: automation testing
Platform: UNKNOWN
Classifier: Development Status :: 3 - Alpha
Classifier: Intended Audience :: Developers
Classifier: Programming Language :: Python :: 3
Classifier: Programming Language :: Python :: 3.6
Requires-Dist: requests
Requires-Dist: paramiko
Requires-Dist: bitpermissions (>=0.1.0)
Requires-Dist: asyncssh
Requires-Dist: aiohttp (>=3.8.1)
Provides-Extra: test
Requires-Dist: pytest (>=2.9.0) ; extra == 'test'
Requires-Dist: flake8 ; extra == 'test'
Requires-Dist: tenacity ; extra == 'test'
